california_midasapi/Midas.py
california_midasapi/__init__.py
california_midasapi/authentication.py
california_midasapi/exception.py
california_midasapi/internal.py
california_midasapi/ratelist.py
california_midasapi/types.py
california_midasapi-1.1.0.dist-info/licenses/LICENSE.md
california_midasapi-1.1.0.dist-info/METADATA
california_midasapi-1.1.0.dist-info/WHEEL
california_midasapi-1.1.0.dist-info/top_level.txt
california_midasapi-1.1.0.dist-info/RECORD
