Metadata-Version: 2.4
Name: california-midasapi
Version: 1.1.0
Summary: Python wrapper for California's energy price API MIDAS.
Author-email: MattDahEpic <matt+california-midasapipypi@mattdahepic.com>
License-Expression: MIT
Project-URL: source, https://github.com/MattDahEpic/california-midasapi
Project-URL: issues, https://github.com/MattDahEpic/california-midasapi/issues
Keywords: california,api,energy,midas,price
Classifier: Development Status :: 3 - Alpha
Classifier: Intended Audience :: Developers
Classifier: Topic :: Scientific/Engineering
Classifier: Programming Language :: Python :: 3
License-File: LICENSE.md
Requires-Dist: aiohttp
Requires-Dist: PyJWT
Requires-Dist: python-dateutil
Provides-Extra: dev
Requires-Dist: cryptography>=3.4.0; extra == "dev"
Dynamic: license-file
